accel_mtrng.cp311-win_amd64.pyd
main.py
accel_mtrng-1.0.dist-info/METADATA
accel_mtrng-1.0.dist-info/WHEEL
accel_mtrng-1.0.dist-info/top_level.txt
accel_mtrng-1.0.dist-info/RECORD
